channels_kafka/__init__.py
channels_kafka/core.py
channels_kafka/multiqueue.py
channels_kafka/util.py
channels_kafka-0.1.1.dist-info/METADATA
channels_kafka-0.1.1.dist-info/WHEEL
channels_kafka-0.1.1.dist-info/licenses/LICENSE
channels_kafka-0.1.1.dist-info/RECORD
