Metadata-Version: 2.4
Name: channels-kafka
Version: 0.1.1
Summary: Kafka Channels backend
Project-URL: Homepage, https://github.com/PawelKawula/channels-kafka
Project-URL: Repository, https://github.com/PawelKawula/channels-kafka
Author-email: Paweł Kawula <pawel.kawula@proton.me>
License-Expression: MIT
License-File: LICENSE
Keywords: channels,kafka
Classifier: Operating System :: OS Independent
Classifier: Programming Language :: Python :: 3
Classifier: Programming Language :: Python :: 3.11
Classifier: Programming Language :: Python :: 3.12
Classifier: Programming Language :: Python :: 3.13
Classifier: Programming Language :: Python :: 3.14
Requires-Python: >=3.11
Requires-Dist: aiokafka
Requires-Dist: channels<5,>=3
Requires-Dist: msgpack>=1.1.0
